[
  {
    "mal_id": 52991,
    "images": {
      "webp": {
        "image_url": "https://cdn.myanimelist.net/images/anime/1015/138006.webp"
      }
    },
    "title": "Sousou no Frieren",
    "score": 9.33
  },
  {
    "mal_id": 5114,
    "images": {
      "webp": {
        "image_url": "https://cdn.myanimelist.net/images/anime/1208/94745.webp"
      }
    },
    "title": "Fullmetal Alchemist: Brotherhood",
    "score": 9.09
  },
  {
    "mal_id": 9253,
    "images": {
      "webp": {
        "image_url": "https://cdn.myanimelist.net/images/anime/1935/127974.webp"
      }
    },
    "title": "Steins;Gate",
    "score": 9.07
  },
  {
    "mal_id": 56784,
    "images": {
      "webp": {
        "image_url": "https://cdn.myanimelist.net/images/anime/1595/144074.webp"
      }
    },
    "title": "Bleach: Sennen Kessen-hen - Soukoku-tan",
    "score": 9.06
  },
  {
    "mal_id": 28977,
    "images": {
      "webp": {
        "image_url": "https://cdn.myanimelist.net/images/anime/3/72078.webp"
      }
    },
    "title": "Gintama°",
    "score": 9.05
  },
  {
    "mal_id": 38524,
    "images": {
      "webp": {
        "image_url": "https://cdn.myanimelist.net/images/anime/1517/100633.webp"
      }
    },
    "title": "Shingeki no Kyojin Season 3 Part 2",
    "score": 9.05
  },
  {
    "mal_id": 11061,
    "images": {
      "webp": {
        "image_url": "https://cdn.myanimelist.net/images/anime/1337/99013.webp"
      }
    },
    "title": "Hunter x Hunter (2011)",
    "score": 9.03
  },
  {
    "mal_id": 9969,
    "images": {
      "webp": {
        "image_url": "https://cdn.myanimelist.net/images/anime/4/50361.webp"
      }
    },
    "title": "Gintama'",
    "score": 9.03
  },
  {
    "mal_id": 15417,
    "images": {
      "webp": {
        "image_url": "https://cdn.myanimelist.net/images/anime/1452/123686.webp"
      }
    },
    "title": "Gintama': Enchousen",
    "score": 9.02
  }
]
